ntfy_catch/__init__.py
ntfy_catch/action_dispatcher.py
ntfy_catch/ai_classifier.py
ntfy_catch/config_loader.py
ntfy_catch/logger_setup.py
ntfy_catch/main.py
ntfy_catch/poller.py
ntfy_catch/state_manager.py
ntfy_catch/examples/crontab-entry.txt
ntfy_catch/examples/handler-example.py
ntfy_catch/examples/ntfy-catch.ini.example
ntfy_catch-0.2.2.dist-info/METADATA
ntfy_catch-0.2.2.dist-info/WHEEL
ntfy_catch-0.2.2.dist-info/entry_points.txt
ntfy_catch-0.2.2.dist-info/RECORD
