Metadata-Version: 2.4
Name: ntfy_catch
Version: 0.2.2
Summary: catch ntfy message
Author-email: jaromrax <jaromrax@gmail.com>
Requires-Python: >=3.10.0
Requires-Dist: requests>=2.32.5
